aind_dynamic_foraging_population_analysis/__init__.py
aind_dynamic_foraging_population_analysis-0.0.1.dist-info/LICENSE
aind_dynamic_foraging_population_analysis-0.0.1.dist-info/METADATA
aind_dynamic_foraging_population_analysis-0.0.1.dist-info/WHEEL
aind_dynamic_foraging_population_analysis-0.0.1.dist-info/top_level.txt
aind_dynamic_foraging_population_analysis-0.0.1.dist-info/RECORD
