Metadata-Version: 2.2
Name: aind-dynamic-foraging-population-analysis
Version: 0.0.1
Summary: Utils for dynamic foraging population analysis
Author: Allen Institute for Neural Dynamics
Author-email: Han Hou <han.hou@alleninstitute.org>
License: MIT
Classifier: Programming Language :: Python :: 3
Requires-Python: >=3.9
License-File: LICENSE
Provides-Extra: dev
Requires-Dist: black; extra == "dev"
Requires-Dist: coverage; extra == "dev"
Requires-Dist: flake8; extra == "dev"
Requires-Dist: interrogate; extra == "dev"
Requires-Dist: isort; extra == "dev"
Requires-Dist: Sphinx; extra == "dev"
Requires-Dist: furo; extra == "dev"
